{
    "properties": [
        {
            "name": "jwt.secret",
            "type": "java.lang.String",
            "description": "Clave de jwt"
        },
        {
            "name": "jwt.expiration-ms",
            "type": "java.lang.Long",
            "description": "Tiempo expiración del token en milisegundos"
        },
        {
            "name": "correo.username",
            "type": "java.lang.String",
            "description": "Correo electrónico para enviar emails"
        },
        {
            "name": "correo.password",
            "type": "java.lang.String",
            "description": "Contraseña del correo electrónico"
        }
    ]
}